xpath/__init__.py
xpath/exceptions.py
xpath/expr.py
xpath/parser.py
xpath/yappsrt.py
yapps2/parsedesc.py
yapps2/yapps2.py
yapps2/yappsrt.py
py_dom_xpath_six-0.2.4.dist-info/LICENSE
py_dom_xpath_six-0.2.4.dist-info/METADATA
py_dom_xpath_six-0.2.4.dist-info/WHEEL
py_dom_xpath_six-0.2.4.dist-info/top_level.txt
py_dom_xpath_six-0.2.4.dist-info/RECORD
