Metadata-Version: 2.1
Name: py-dom-xpath-six
Version: 0.2.4
Summary: XPath for DOM trees
Home-page: https://github.com/jackjansen/py-dom-xpath-six
Author: Damien Neil
Author-email: damien.neil@gmail.com
Maintainer: Jack Jansen
Maintainer-email: Jack.Jansen@cwi.nl
License: UNKNOWN
Project-URL: Bug Tracker, https://github.com/pypa/sampleproject/issues
Platform: UNKNOWN
Classifier: Programming Language :: Python :: 3
Classifier: License :: OSI Approved :: MIT License
Classifier: Operating System :: OS Independent
Classifier: Topic :: Text Processing :: Markup :: XML
License-File: LICENSE
